{
    "data":[
      {
        "src": "/assets/gallery/mams_day/mam_1.jpg",
        "previewImageSrc": "1eHLGD52_VcIk8g5w87V6zsj6bPuY-z-a",
        "thumbnailImageSrc": "1fNL_j8zVVrk4R_zUeBZXwem1FdK2yN6F",
        "alt": "Description for Image 1",
        "title": "File1"
      },
      {
        "src": "/assets/gallery/mams_day/mam_2.jpg",
        "previewImageSrc": "1eHLGD52_VcIk8g5w87V6zsj6bPuY-z-a",
        "thumbnailImageSrc": "1fNL_j8zVVrk4R_zUeBZXwem1FdK2yN6F",
        "alt": "Description for Image 1",
        "title": "File1"
      },
      {
        "src": "/assets/gallery/mams_day/mam_3.jpg",
        "previewImageSrc": "1eHLGD52_VcIk8g5w87V6zsj6bPuY-z-a",
        "thumbnailImageSrc": "1fNL_j8zVVrk4R_zUeBZXwem1FdK2yN6F",
        "alt": "Description for Image 1",
        "title": "File1"
      },
      {
        "src": "/assets/gallery/mams_day/mam_4.jpg",
        "previewImageSrc": "1eHLGD52_VcIk8g5w87V6zsj6bPuY-z-a",
        "thumbnailImageSrc": "1fNL_j8zVVrk4R_zUeBZXwem1FdK2yN6F",
        "alt": "Description for Image 1",
        "title": "File1"
      },
      {
        "src": "/assets/gallery/mams_day/mam_5.jpg",
        "previewImageSrc": "1eHLGD52_VcIk8g5w87V6zsj6bPuY-z-a",
        "thumbnailImageSrc": "1fNL_j8zVVrk4R_zUeBZXwem1FdK2yN6F",
        "alt": "Description for Image 1",
        "title": "File1"
      },
      {
        "src": "/assets/gallery/mams_day/mam_7.jpg",
        "previewImageSrc": "1eHLGD52_VcIk8g5w87V6zsj6bPuY-z-a",
        "thumbnailImageSrc": "1fNL_j8zVVrk4R_zUeBZXwem1FdK2yN6F",
        "alt": "Description for Image 1",
        "title": "File1"
      },
      {
        "src": "/assets/gallery/mams_day/mam_8.jpg",
        "previewImageSrc": "1eHLGD52_VcIk8g5w87V6zsj6bPuY-z-a",
        "thumbnailImageSrc": "1fNL_j8zVVrk4R_zUeBZXwem1FdK2yN6F",
        "alt": "Description for Image 1",
        "title": "File1"
      },
      {
        "src": "/assets/gallery/mams_day/mam_9.jpg",
        "previewImageSrc": "1eHLGD52_VcIk8g5w87V6zsj6bPuY-z-a",
        "thumbnailImageSrc": "1fNL_j8zVVrk4R_zUeBZXwem1FdK2yN6F",
        "alt": "Description for Image 1",
        "title": "File1"
      },
      {
        "src": "/assets/gallery/mams_day/mam_10.jpg",
        "previewImageSrc": "1eHLGD52_VcIk8g5w87V6zsj6bPuY-z-a",
        "thumbnailImageSrc": "1fNL_j8zVVrk4R_zUeBZXwem1FdK2yN6F",
        "alt": "Description for Image 1",
        "title": "File1"
      },
      {
        "src": "/assets/gallery/mams_day/mam_11.jpg",
        "previewImageSrc": "1eHLGD52_VcIk8g5w87V6zsj6bPuY-z-a",
        "thumbnailImageSrc": "1fNL_j8zVVrk4R_zUeBZXwem1FdK2yN6F",
        "alt": "Description for Image 1",
        "title": "File1"
      },
      {
        "src": "/assets/gallery/mams_day/mam_12.jpg",
        "previewImageSrc": "1eHLGD52_VcIk8g5w87V6zsj6bPuY-z-a",
        "thumbnailImageSrc": "1fNL_j8zVVrk4R_zUeBZXwem1FdK2yN6F",
        "alt": "Description for Image 1",
        "title": "File1"
      },
      {
        "src": "/assets/gallery/mams_day/mam_13.jpg",
        "previewImageSrc": "1eHLGD52_VcIk8g5w87V6zsj6bPuY-z-a",
        "thumbnailImageSrc": "1fNL_j8zVVrk4R_zUeBZXwem1FdK2yN6F",
        "alt": "Description for Image 1",
        "title": "File1"
      },
      {
        "src": "/assets/gallery/mams_day/mam_14.jpg",
        "previewImageSrc": "1eHLGD52_VcIk8g5w87V6zsj6bPuY-z-a",
        "thumbnailImageSrc": "1fNL_j8zVVrk4R_zUeBZXwem1FdK2yN6F",
        "alt": "Description for Image 1",
        "title": "File1"
      },
      {
        "src": "/assets/gallery/mams_day/mam_15.jpg",
        "previewImageSrc": "1eHLGD52_VcIk8g5w87V6zsj6bPuY-z-a",
        "thumbnailImageSrc": "1fNL_j8zVVrk4R_zUeBZXwem1FdK2yN6F",
        "alt": "Description for Image 1",
        "title": "File1"
      },
      {
        "src": "/assets/gallery/mams_day/mam_16.jpg",
        "previewImageSrc": "1eHLGD52_VcIk8g5w87V6zsj6bPuY-z-a",
        "thumbnailImageSrc": "1fNL_j8zVVrk4R_zUeBZXwem1FdK2yN6F",
        "alt": "Description for Image 1",
        "title": "File1"
      },
      {
        "src": "/assets/gallery/mams_day/mam_20.jpg",
        "previewImageSrc": "1eHLGD52_VcIk8g5w87V6zsj6bPuY-z-a",
        "thumbnailImageSrc": "1fNL_j8zVVrk4R_zUeBZXwem1FdK2yN6F",
        "alt": "Description for Image 1",
        "title": "File1"
      },
      {
        "src": "/assets/gallery/mams_day/mam_18.jpg",
        "previewImageSrc": "1eHLGD52_VcIk8g5w87V6zsj6bPuY-z-a",
        "thumbnailImageSrc": "1fNL_j8zVVrk4R_zUeBZXwem1FdK2yN6F",
        "alt": "Description for Image 1",
        "title": "File1"
      },
      {
        "src": "/assets/gallery/mams_day/mam_19.jpg",
        "previewImageSrc": "1eHLGD52_VcIk8g5w87V6zsj6bPuY-z-a",
        "thumbnailImageSrc": "1fNL_j8zVVrk4R_zUeBZXwem1FdK2yN6F",
        "alt": "Description for Image 1",
        "title": "File1"
      },
      {
        "src": "/assets/gallery/mams_day/mam_21.jpg",
        "previewImageSrc": "1eHLGD52_VcIk8g5w87V6zsj6bPuY-z-a",
        "thumbnailImageSrc": "1fNL_j8zVVrk4R_zUeBZXwem1FdK2yN6F",
        "alt": "Description for Image 1",
        "title": "File1"
      },
      {
        "src": "/assets/gallery/mams_day/mam_6.jpg",
        "previewImageSrc": "1eHLGD52_VcIk8g5w87V6zsj6bPuY-z-a",
        "thumbnailImageSrc": "1fNL_j8zVVrk4R_zUeBZXwem1FdK2yN6F",
        "alt": "Description for Image 1",
        "title": "File1"
      },
      {
        "src": "/assets/gallery/mams_day/mam_17.jpg",
        "previewImageSrc": "1eHLGD52_VcIk8g5w87V6zsj6bPuY-z-a",
        "thumbnailImageSrc": "1fNL_j8zVVrk4R_zUeBZXwem1FdK2yN6F",
        "alt": "Description for Image 1",
        "title": "File1"
      },
      {
        "src": "/assets/gallery/mams_day/mam_single1.jpg",
        "previewImageSrc": "1eHLGD52_VcIk8g5w87V6zsj6bPuY-z-a",
        "thumbnailImageSrc": "1fNL_j8zVVrk4R_zUeBZXwem1FdK2yN6F",
        "alt": "Description for Image 1",
        "title": "File1"
      },
      {
        "src": "/assets/gallery/mams_day/mam24.jpg",
        "previewImageSrc": "1eHLGD52_VcIk8g5w87V6zsj6bPuY-z-a",
        "thumbnailImageSrc": "1fNL_j8zVVrk4R_zUeBZXwem1FdK2yN6F",
        "alt": "Description for Image 1",
        "title": "File1"
      },
      {
        "src": "/assets/gallery/mams_day/pic_single3.jpg",
        "previewImageSrc": "1eHLGD52_VcIk8g5w87V6zsj6bPuY-z-a",
        "thumbnailImageSrc": "1fNL_j8zVVrk4R_zUeBZXwem1FdK2yN6F",
        "alt": "Description for Image 1",
        "title": "File1"
      },
      {
        "src": "/assets/gallery/mams_day/mam_single.jpg",
        "previewImageSrc": "1eHLGD52_VcIk8g5w87V6zsj6bPuY-z-a",
        "thumbnailImageSrc": "1fNL_j8zVVrk4R_zUeBZXwem1FdK2yN6F",
        "alt": "Description for Image 1",
        "title": "File1"
      }
      ,
      {
        "src": "/assets/gallery/mams_day/mam_single5.jpg",
        "previewImageSrc": "1eHLGD52_VcIk8g5w87V6zsj6bPuY-z-a",
        "thumbnailImageSrc": "1fNL_j8zVVrk4R_zUeBZXwem1FdK2yN6F",
        "alt": "Description for Image 1",
        "title": "File1"
      },
      {
        "src": "/assets/gallery/mams_day/mam_single4.jpg",
        "previewImageSrc": "1eHLGD52_VcIk8g5w87V6zsj6bPuY-z-a",
        "thumbnailImageSrc": "1fNL_j8zVVrk4R_zUeBZXwem1FdK2yN6F",
        "alt": "Description for Image 1",
        "title": "File1"
      },
      {
        "src": "/assets/gallery/mams_day/mam20.jpg",
        "previewImageSrc": "1eHLGD52_VcIk8g5w87V6zsj6bPuY-z-a",
        "thumbnailImageSrc": "1fNL_j8zVVrk4R_zUeBZXwem1FdK2yN6F",
        "alt": "Description for Image 1",
        "title": "File1"
      },
      {
        "src": "/assets/gallery/mams_day/mam21.jpg",
        "previewImageSrc": "1eHLGD52_VcIk8g5w87V6zsj6bPuY-z-a",
        "thumbnailImageSrc": "1fNL_j8zVVrk4R_zUeBZXwem1FdK2yN6F",
        "alt": "Description for Image 1",
        "title": "File1"
      },
      {
        "src": "/assets/gallery/mams_day/mam22.jpg",
        "previewImageSrc": "1eHLGD52_VcIk8g5w87V6zsj6bPuY-z-a",
        "thumbnailImageSrc": "1fNL_j8zVVrk4R_zUeBZXwem1FdK2yN6F",
        "alt": "Description for Image 1",
        "title": "File1"
      },
      {
        "src": "/assets/gallery/mams_day/mam23.jpg",
        "previewImageSrc": "1eHLGD52_VcIk8g5w87V6zsj6bPuY-z-a",
        "thumbnailImageSrc": "1fNL_j8zVVrk4R_zUeBZXwem1FdK2yN6F",
        "alt": "Description for Image 1",
        "title": "File1"
      },
      {
        "src": "/assets/gallery/mams_day/mam25.jpg",
        "previewImageSrc": "1eHLGD52_VcIk8g5w87V6zsj6bPuY-z-a",
        "thumbnailImageSrc": "1fNL_j8zVVrk4R_zUeBZXwem1FdK2yN6F",
        "alt": "Description for Image 1",
        "title": "File1"
      },
      {
        "src": "/assets/gallery/mams_day/mam27.jpg",
        "previewImageSrc": "1eHLGD52_VcIk8g5w87V6zsj6bPuY-z-a",
        "thumbnailImageSrc": "1fNL_j8zVVrk4R_zUeBZXwem1FdK2yN6F",
        "alt": "Description for Image 1",
        "title": "File1"
      },
      {
        "src": "/assets/gallery/mams_day/pic_69.jpg",
        "previewImageSrc": "1eHLGD52_VcIk8g5w87V6zsj6bPuY-z-a",
        "thumbnailImageSrc": "1fNL_j8zVVrk4R_zUeBZXwem1FdK2yN6F",
        "alt": "Description for Image 1",
        "title": "File1"
      },
      {
        "src": "/assets/gallery/mams_day/pic_group.jpg",
        "previewImageSrc": "1eHLGD52_VcIk8g5w87V6zsj6bPuY-z-a",
        "thumbnailImageSrc": "1fNL_j8zVVrk4R_zUeBZXwem1FdK2yN6F",
        "alt": "Description for Image 1",
        "title": "File1"
      },
      {
        "src": "/assets/gallery/mams_day/pic_single.jpg",
        "previewImageSrc": "1eHLGD52_VcIk8g5w87V6zsj6bPuY-z-a",
        "thumbnailImageSrc": "1fNL_j8zVVrk4R_zUeBZXwem1FdK2yN6F",
        "alt": "Description for Image 1",
        "title": "File1"
      },
      {
        "src": "/assets/gallery/mams_day/pic_70.jpg",
        "previewImageSrc": "1eHLGD52_VcIk8g5w87V6zsj6bPuY-z-a",
        "thumbnailImageSrc": "1fNL_j8zVVrk4R_zUeBZXwem1FdK2yN6F",
        "alt": "Description for Image 1",
        "title": "File1"
      },
      {
        "src": "/assets/gallery/mams_day/pic63.jpg",
        "previewImageSrc": "1eHLGD52_VcIk8g5w87V6zsj6bPuY-z-a",
        "thumbnailImageSrc": "1fNL_j8zVVrk4R_zUeBZXwem1FdK2yN6F",
        "alt": "Description for Image 1",
        "title": "File1"
      },
      {
        "src": "/assets/gallery/mams_day/pic_73.jpg",
        "previewImageSrc": "1eHLGD52_VcIk8g5w87V6zsj6bPuY-z-a",
        "thumbnailImageSrc": "1fNL_j8zVVrk4R_zUeBZXwem1FdK2yN6F",
        "alt": "Description for Image 1",
        "title": "File1"
      },
      {
        "src": "/assets/gallery/mams_day/pic_71.jpg",
        "previewImageSrc": "1eHLGD52_VcIk8g5w87V6zsj6bPuY-z-a",
        "thumbnailImageSrc": "1fNL_j8zVVrk4R_zUeBZXwem1FdK2yN6F",
        "alt": "Description for Image 1",
        "title": "File1"
      },
      {
        "src": "/assets/gallery/mams_day/pic_72.jpg",
        "previewImageSrc": "1eHLGD52_VcIk8g5w87V6zsj6bPuY-z-a",
        "thumbnailImageSrc": "1fNL_j8zVVrk4R_zUeBZXwem1FdK2yN6F",
        "alt": "Description for Image 1",
        "title": "File1"
      },
      {
        "src": "/assets/gallery/mams_day/pic41.jpg",
        "previewImageSrc": "1eHLGD52_VcIk8g5w87V6zsj6bPuY-z-a",
        "thumbnailImageSrc": "1fNL_j8zVVrk4R_zUeBZXwem1FdK2yN6F",
        "alt": "Description for Image 1",
        "title": "File1"
      }
    
    ]
  }

 

